RL22021UNO/__init__.py
RL22021UNO/biseccion.py
RL22021UNO/cramer.py
RL22021UNO/gauss.py
RL22021UNO/gauss_jordan.py
RL22021UNO/gauss_seidel.py
RL22021UNO/jacobi.py
RL22021UNO/lu.py
tests/__init__.py
tests/test_biseccion.py
tests/test_cramer.py
tests/test_gauss.py
tests/test_gaussjordan.py
tests/test_jacobi.py
tests/test_lu.py
rl22021uno-1.0.0.dist-info/METADATA
rl22021uno-1.0.0.dist-info/WHEEL
rl22021uno-1.0.0.dist-info/top_level.txt
rl22021uno-1.0.0.dist-info/RECORD
