Metadata-Version: 2.4
Name: RL22021UNO
Version: 1.0.0
Summary: Librería para resolver sistemas de ecuaciones lineales y no lineales
Home-page: https://github.com/Mirna1111/RL22021UNO
Author: Mirna Rivas
Author-email: mirnarivas860@gmail.com
Classifier: Programming Language :: Python :: 3
Classifier: License :: OSI Approved :: MIT License
Classifier: Operating System :: OS Independent
Requires-Python: >=3.6
Requires-Dist: numpy
Dynamic: author
Dynamic: author-email
Dynamic: classifier
Dynamic: description
Dynamic: description-content-type
Dynamic: home-page
Dynamic: requires-dist
Dynamic: requires-python
Dynamic: summary
